{
    "faq": {
        "badge": "الأسئلة الشائعة",
        "title": "الأسئلة",
        "titleAccent": "المتكررة",
        "items": [
            {
                "id": 1,
                "question": "كم من الوقت يستغرق المشروع عادة؟",
                "answer": "يستغرق المشروع العادي من شهرين إلى 6 أشهر حسب التعقيد والنطاق."
            },
            {
                "id": 2,
                "question": "هل تقدمون خدمة تصميم الأثاث المخصص؟",
                "answer": "نعم، نحن نتعاون مع حرفيين خبراء لإنشاء أثاث مخصص يناسب مساحتك تماماً."
            },
            {
                "id": 3,
                "question": "هل يمكنني رؤية أعمالكم السابقة؟",
                "answer": "بالتأكيد! يمكنك مراجعة قسم المعرض والمشاريع لدينا لرؤية محفظة أعمالنا."
            }
        ]
    }
}